{
   "error":true,
   "maintainers":[{"main_maintainer":false,
   "github_username":"waiser86",
   "name":"Dmitry"}],
   "donate_url":"https://yoomoney.ru/to/410014701035999",
   "website_url":"https://romodel.ru",
   "news_url":"https:\/\/t.me\/romodel",
   "url":"https://ota.romodel.ru/PixelExperience_Plus_vayu-11.0-20210916-0628-ROMODEL.RU.zip",
   "version":"eleven-go",
   "datetime": 1631773680,
   "filehash": "aef8fa4cde767329f2f8ec3177fad523",
   "filename": "PixelExperience_Plus_vayu-11.0-20210916-0628-ROMODEL.RU.zip",
   "id": "709c9691fe4cbeb336292381743893aa40d2d64542df4ced75b250bd48716d29",
   "size": 1668704407
}
